libvalkey/version.py
libvalkey/libvalkey.pyi
libvalkey/libvalkey.cpython-312-s390x-linux-gnu.so
libvalkey/py.typed
libvalkey/__init__.py
libvalkey-4.0.1.dist-info/RECORD
libvalkey-4.0.1.dist-info/METADATA
libvalkey-4.0.1.dist-info/WHEEL
libvalkey-4.0.1.dist-info/top_level.txt
libvalkey-4.0.1.dist-info/LICENSE
