Metadata-Version: 2.1
Name: libvalkey
Version: 4.0.1
Summary: Python wrapper for libvalkey
Home-page: https://github.com/valkey-io/libvalkey-py
Author: libvalkey-py authors
Author-email: libvalkey-py@lists.valkey.io
License: MIT
Project-URL: Changes, https://github.com/valkey-io/libvalkey-py/releases
Project-URL: Issue tracker, https://github.com/valkey-io/libvalkey-py/issues
Keywords: Valkey
Classifier: Development Status :: 5 - Production/Stable
Classifier: Intended Audience :: Developers
Classifier: License :: OSI Approved :: MIT License
Classifier: Operating System :: MacOS
Classifier: Operating System :: POSIX
Classifier: Programming Language :: C
Classifier: Programming Language :: Python :: 3
Classifier: Programming Language :: Python :: 3 :: Only
Classifier: Programming Language :: Python :: 3.8
Classifier: Programming Language :: Python :: 3.9
Classifier: Programming Language :: Python :: 3.10
Classifier: Programming Language :: Python :: 3.11
Classifier: Programming Language :: Python :: 3.12
Classifier: Programming Language :: Python :: 3.13
Classifier: Programming Language :: Python :: Implementation :: CPython
Classifier: Topic :: Software Development
Requires-Python: >=3.8
License-File: LICENSE
